chatgpt_automation/__init__.py
chatgpt_automation/chatgpt_automation.py
chatgpt_automation/chromedriver_manager.py
mytest/__init__.py
mytest/index.py
mytest/new_test.py
mytest/test.py
tests/__init__.py
tests/test_chatgpt_automation.py
ChatGPTAutomation-0.7.3.dist-info/LICENCE.md
ChatGPTAutomation-0.7.3.dist-info/METADATA
ChatGPTAutomation-0.7.3.dist-info/WHEEL
ChatGPTAutomation-0.7.3.dist-info/top_level.txt
ChatGPTAutomation-0.7.3.dist-info/RECORD
