Metadata-Version: 2.1
Name: ChatGPTAutomation
Version: 0.7.3
Summary: A Python package for automating interactions with ChatGPT using Selenium. Chatgpt automation without api. Chatgptautomation
Home-page: https://github.com/iamseyedalipro/ChatGPTAutomation
Author: Seyed Ali Hosseini
Author-email: iamseyedalipro@gmail.com
Project-URL: Documentation, https://github.com/iamseyedalipro/ChatGPTAutomation#readme
Project-URL: Source, https://github.com/iamseyedalipro/ChatGPTAutomation
Project-URL: Tracker, https://github.com/iamseyedalipro/ChatGPTAutomation/issues
Keywords: ChatGPT automation,Chatgpt Automation without api,chatgpt selenium,chatgpt selenium automation,Selenium integration,OpenAI chatbot,test automation,web automation,GPT-3,GPT-4,file upload automation,chat history retrieval,login automation,software testing,QA tools,automation engineers,Python library,automation framework,pytest integration,robot framework,browser automation,automated testing,AI chatbot automation,web driver tools
Classifier: Development Status :: 3 - Alpha
Classifier: Intended Audience :: Developers
Classifier: Topic :: Software Development :: Testing
Classifier: License :: OSI Approved :: MIT License
Classifier: Programming Language :: Python :: 3
Classifier: Programming Language :: Python :: 3.8
Classifier: Programming Language :: Python :: 3.9
Classifier: Programming Language :: Python :: 3.10
Requires-Python: >=3.8
License-File: LICENCE.md
Requires-Dist: python-dotenv ==1.0.0
Requires-Dist: pywin32 ==306
Requires-Dist: pyzmq ==25.1.1
Requires-Dist: requests ==2.31.0
Requires-Dist: selenium ==4.9.0
Requires-Dist: webdriver-manager ==4.0.1
Requires-Dist: pyperclip ==1.9.0
Requires-Dist: PyAutoIt ==0.6.5
